minesweeper/__init__.py
minesweeper/core/__init__.py
minesweeper/core/board.py
minesweeper/core/board_tile.py
pygame_minesweeper_core-1.0.18.dist-info/LICENSE
pygame_minesweeper_core-1.0.18.dist-info/METADATA
pygame_minesweeper_core-1.0.18.dist-info/WHEEL
pygame_minesweeper_core-1.0.18.dist-info/top_level.txt
pygame_minesweeper_core-1.0.18.dist-info/RECORD
