Metadata-Version: 2.1
Name: pygame-minesweeper-core
Version: 1.0.18
Summary: Minesweeper game core library
Home-page: https://github.com/andreasisnes/Elitekollektivet.Minesweeper.Core
Author: Andreas Isnes Nilsen
Author-email: andreas.isnes@gmail.com
License: UNKNOWN
Platform: UNKNOWN
Classifier: Programming Language :: Python :: 3
Classifier: License :: OSI Approved :: MIT License
Classifier: Operating System :: OS Independent
